autoparsed_address_field/__init__.py
autoparsed_address_field/admin.py
autoparsed_address_field/apps.py
autoparsed_address_field/descriptors.py
autoparsed_address_field/fields.py
autoparsed_address_field/mixins.py
autoparsed_address_field/signals.py
autoparsed_address_field/migrations/0001_initial.py
autoparsed_address_field/migrations/0002_address_address_id_alter_address_address_line_1_and_more.py
autoparsed_address_field/migrations/__init__.py
autoparsed_address_field/models/__init__.py
autoparsed_address_field/models/address.py
autoparsed_address_field/models/country.py
autoparsed_address_field/models/locality.py
autoparsed_address_field/models/state.py
autoparsed_address_field/services/__init__.py
autoparsed_address_field/services/arcgis.py
autoparsed_address_field/services/scourgify.py
autoparsed_address_field/tests/__init__.py
autoparsed_address_field/tests/test_admin.py
autoparsed_address_field/tests/test_descriptors.py
autoparsed_address_field/tests/test_fields.py
autoparsed_address_field/tests/test_mixins.py
autoparsed_address_field/tests/test_models_address.py
autoparsed_address_field/tests/test_models_country.py
autoparsed_address_field/tests/test_models_locality.py
autoparsed_address_field/tests/test_models_state.py
autoparsed_address_field/tests/test_services_arcgis.py
autoparsed_address_field/tests/test_services_scourgify.py
autoparsed_address_field/tests/test_signals.py
autoparsed_address_field/tests/test_utils.py
autoparsed_address_field/tests/test_utils_uuid.py
autoparsed_address_field/utils/__init__.py
autoparsed_address_field/utils/create_address_from_keys.py
autoparsed_address_field/utils/uuid.py
django_autoparsed_address_field-1.0.3.dist-info/LICENSE
django_autoparsed_address_field-1.0.3.dist-info/METADATA
django_autoparsed_address_field-1.0.3.dist-info/WHEEL
django_autoparsed_address_field-1.0.3.dist-info/top_level.txt
django_autoparsed_address_field-1.0.3.dist-info/RECORD
