Metadata-Version: 2.1
Name: django-autoparsed-address-field
Version: 1.0.3
Summary: A Django package to manage and parse addresses with geocoding support.
Home-page: https://github.com/rzwink/django-autoparsed-address-field
Author: Robert Zwink
Author-email: rob@zwink.net
License: MIT
Classifier: Development Status :: 3 - Alpha
Classifier: Environment :: Web Environment
Classifier: Framework :: Django
Classifier: Framework :: Django :: 3.2
Classifier: Framework :: Django :: 4.0
Classifier: Framework :: Django :: 4.1
Classifier: Intended Audience :: Developers
Classifier: License :: OSI Approved :: MIT License
Classifier: Operating System :: OS Independent
Classifier: Programming Language :: Python
Classifier: Programming Language :: Python :: 3.8
Classifier: Programming Language :: Python :: 3.9
Classifier: Programming Language :: Python :: 3.10
Classifier: Programming Language :: Python :: 3.11
Classifier: Programming Language :: Python :: 3.12
Classifier: Topic :: Software Development :: Libraries :: Python Modules
Requires-Python: >=3.8
License-File: LICENSE
Requires-Dist: django>=3.2
Requires-Dist: geopy>=2.4.1
Requires-Dist: usaddress-scourgify>=0.6.0
Requires-Dist: uszipcode>=1.0.1
Requires-Dist: sqlalchemy-mate==1.4.28.4
Requires-Dist: python-Levenshtein>=0.26.1
Provides-Extra: dev
Requires-Dist: pytest; extra == "dev"
Requires-Dist: pytest-django; extra == "dev"
Requires-Dist: black; extra == "dev"
Requires-Dist: flake8; extra == "dev"
Requires-Dist: pre-commit; extra == "dev"
